README.rst
setup.py
aiofnbr/__init__.py
aiofnbr/constants.py
aiofnbr/core.py
aiofnbr/utils.py
fnbr/__init__.py
fnbr/constants.py
fnbr/core.py
fnbr/utils.py
fnbr_api.egg-info/PKG-INFO
fnbr_api.egg-info/SOURCES.txt
fnbr_api.egg-info/dependency_links.txt
fnbr_api.egg-info/requires.txt
fnbr_api.egg-info/top_level.txt