Metadata-Version: 1.1
Name: fnbr-api
Version: 1.1.3
Summary: Python wrapper of the fnbr.co fortnite shop API for ease of use in a python enviroment.
Home-page: https://github.com/Douile/fnbr-api
Author: Douile
Author-email: UNKNOWN
License: MIT
Keywords: API fortnite fnbr
Platform: UNKNOWN
Classifier: Development Status :: 4 - Beta
Classifier: Intended Audience :: Developers
Classifier: License :: OSI Approved :: MIT License
